{
  "userConfigMajorVersion": 6,
  "userConfigMinorVersion": 0,
  "userConfigPatchVersion": 0,
  "deviceName": "My UHK",
  "doubleTapSwitchLayerTimeout": 250,
  "iconsAndLayerTextsBrightness": 129,
  "alphanumericSegmentsBrightness": 130,
  "keyBacklightBrightness": 255,
  "ledsFadeTimeout": 0,
  "perKeyRgbPresent": false,
  "backlightingMode": 0,
  "backlightingNoneActionColor": {
    "b": 0,
    "g": 0,
    "r": 0
  },
  "backlightingScancodeColor": {
    "b": 255,
    "g": 255,
    "r": 255
  },
  "backlightingModifierColor": {
    "b": 255,
    "g": 255,
    "r": 0
  },
  "backlightingShortcutColor": {
    "b": 255,
    "g": 0,
    "r": 0
  },
  "backlightingSwitchLayerColor": {
    "b": 0,
    "g": 255,
    "r": 255
  },
  "backlightingSwitchKeymapColor": {
    "b": 0,
    "g": 0,
    "r": 255
  },
  "backlightingMouseColor": {
    "b": 0,
    "g": 255,
    "r": 0
  },
  "backlightingMacroColor": {
    "b": 255,
    "g": 0,
    "r": 255
  },
  "mouseMoveInitialSpeed": 6,
  "mouseMoveAcceleration": 80,
  "mouseMoveDeceleratedSpeed": 16,
  "mouseMoveBaseSpeed": 49,
  "mouseMoveAcceleratedSpeed": 64,
  "mouseScrollInitialSpeed": 20,
  "mouseScrollAcceleration": 20,
  "mouseScrollDeceleratedSpeed": 10,
  "mouseScrollBaseSpeed": 20,
  "mouseScrollAcceleratedSpeed": 50,
  "moduleConfigurations": [],
  "keymaps": [
    {
      "isDefault": false,
      "abbreviation": "GAM",
      "name": "Game",
      "description": "main layout",
      "layers": [
        {
          "id": "base",
          "modules": [
            {
              "id": 0,
              "keyActions": [
                {
                  "keyActionType": "keystroke",
                  "type": "basic",
                  "scancode": 36
                },
                {
                  "keyActionType": "keystroke",
                  "type": "basic",
                  "scancode": 37
                },
                {
                  "keyActionType": "keystroke",
                  "type": "basic",
                  "scancode": 38
                },
                {
                  "keyActionType": "keystroke",
                  "type": "basic",
                  "scancode": 39
                },
                {
                  "keyActionType": "keystroke",
                  "type": "basic",
                  "scancode": 45
                },
                {
                  "keyActionType": "keystroke",
                  "type": "basic",
                  "scancode": 46
                },
                {
                  "keyActionType": "keystroke",
                  "type": "basic",
                  "scancode": 42
                },
                {
                  "keyActionType": "keystroke",
                  "type": "basic",
                  "scancode": 24
                },
                {
                  "keyActionType": "keystroke",
                  "type": "basic",
                  "scancode": 12
                },
                {
                  "keyActionType": "keystroke",
                  "type": "basic",
                  "scancode": 18
                },
                {
                  "keyActionType": "keystroke",
                  "type": "basic",
                  "scancode": 19
                },
                {
                  "keyActionType": "keystroke",
                  "type": "basic",
                  "scancode": 47
                },
                {
                  "keyActionType": "keystroke",
                  "type": "basic",
                  "scancode": 48
                },
                {
                  "keyActionType": "keystroke",
                  "type": "basic",
                  "scancode": 49
                },
                {
                  "keyActionType": "keystroke",
                  "type": "basic",
                  "scancode": 28
                },
                {
                  "keyActionType": "keystroke",
                  "type": "basic",
                  "scancode": 13
                },
                {
                  "keyActionType": "keystroke",
                  "type": "basic",
                  "scancode": 14
                },
                {
                  "keyActionType": "keystroke",
                  "type": "basic",
                  "scancode": 15
                },
                {
                  "keyActionType": "keystroke",
                  "type": "basic",
                  "scancode": 51
                },
                {
                  "keyActionType": "keystroke",
                  "type": "basic",
                  "scancode": 52
                },
                {
                  "keyActionType": "keystroke",
                  "type": "basic",
                  "scancode": 40
                },
                {
                  "keyActionType": "keystroke",
                  "type": "basic",
                  "scancode": 11
                },
                {
                  "keyActionType": "keystroke",
                  "type": "basic",
                  "scancode": 17
                },
                {
                  "keyActionType": "keystroke",
                  "type": "basic",
                  "scancode": 16
                },
                {
                  "keyActionType": "keystroke",
                  "type": "basic",
                  "scancode": 54
                },
                {
                  "keyActionType": "keystroke",
                  "type": "basic",
                  "scancode": 55
                },
                {
                  "keyActionType": "keystroke",
                  "type": "basic",
                  "scancode": 56
                },
                {
                  "keyActionType": "keystroke",
                  "type": "basic",
                  "modifierMask": 32
                },
                {
                  "keyActionType": "none"
                },
                {
                  "keyActionType": "keystroke",
                  "type": "basic",
                  "scancode": 44
                },
                {
                  "keyActionType": "keystroke",
                  "type": "basic",
                  "scancode": 40
                },
                {
                  "keyActionType": "keystroke",
                  "type": "basic",
                  "modifierMask": 128
                },
                {
                  "keyActionType": "keystroke",
                  "type": "basic",
                  "modifierMask": 64
                },
                {
                  "keyActionType": "switchLayer",
                  "layer": "fn",
                  "switchLayerMode": "hold"
                },
                {
                  "keyActionType": "keystroke",
                  "type": "basic",
                  "modifierMask": 16
                }
              ]
            },
            {
              "id": 1,
              "keyActions": [
                {
                  "keyActionType": "keystroke",
                  "type": "basic",
                  "scancode": 53
                },
                {
                  "keyActionType": "keystroke",
                  "type": "basic",
                  "scancode": 30
                },
                {
                  "keyActionType": "keystroke",
                  "type": "basic",
                  "scancode": 31
                },
                {
                  "keyActionType": "keystroke",
                  "type": "basic",
                  "scancode": 32
                },
                {
                  "keyActionType": "keystroke",
                  "type": "basic",
                  "scancode": 33
                },
                {
                  "keyActionType": "keystroke",
                  "type": "basic",
                  "scancode": 34
                },
                {
                  "keyActionType": "keystroke",
                  "type": "basic",
                  "scancode": 35
                },
                {
                  "keyActionType": "keystroke",
                  "type": "basic",
                  "scancode": 43
                },
                {
                  "keyActionType": "keystroke",
                  "type": "basic",
                  "scancode": 20
                },
                {
                  "keyActionType": "keystroke",
                  "type": "basic",
                  "scancode": 26
                },
                {
                  "keyActionType": "keystroke",
                  "type": "basic",
                  "scancode": 8
                },
                {
                  "keyActionType": "keystroke",
                  "type": "basic",
                  "scancode": 21
                },
                {
                  "keyActionType": "none"
                },
                {
                  "keyActionType": "keystroke",
                  "type": "basic",
                  "scancode": 23
                },
                {
                  "keyActionType": "keystroke",
                  "type": "basic",
                  "scancode": 57
                },
                {
                  "keyActionType": "keystroke",
                  "type": "basic",
                  "scancode": 4
                },
                {
                  "keyActionType": "keystroke",
                  "type": "basic",
                  "scancode": 22
                },
                {
                  "keyActionType": "keystroke",
                  "type": "basic",
                  "scancode": 7
                },
                {
                  "keyActionType": "keystroke",
                  "type": "basic",
                  "scancode": 9
                },
                {
                  "keyActionType": "none"
                },
                {
                  "keyActionType": "keystroke",
                  "type": "basic",
                  "scancode": 10
                },
                {
                  "keyActionType": "keystroke",
                  "type": "basic",
                  "modifierMask": 2
                },
                {
                  "keyActionType": "keystroke",
                  "type": "basic",
                  "scancode": 100
                },
                {
                  "keyActionType": "keystroke",
                  "type": "basic",
                  "scancode": 29
                },
                {
                  "keyActionType": "keystroke",
                  "type": "basic",
                  "scancode": 27
                },
                {
                  "keyActionType": "keystroke",
                  "type": "basic",
                  "scancode": 6
                },
                {
                  "keyActionType": "keystroke",
                  "type": "basic",
                  "scancode": 25
                },
                {
                  "keyActionType": "keystroke",
                  "type": "basic",
                  "scancode": 5
                },
                {
                  "keyActionType": "keystroke",
                  "type": "basic",
                  "modifierMask": 1
                },
                {
                  "keyActionType": "switchLayer",
                  "layer": "fn",
                  "switchLayerMode": "hold"
                },
                {
                  "keyActionType": "keystroke",
                  "type": "basic",
                  "modifierMask": 4
                },
                {
                  "keyActionType": "keystroke",
                  "type": "basic",
                  "modifierMask": 8
                },
                {
                  "keyActionType": "keystroke",
                  "type": "basic",
                  "scancode": 44
                },
                {
                  "keyActionType": "switchLayer",
                  "layer": "mod",
                  "switchLayerMode": "hold"
                },
                {
                  "keyActionType": "none"
                }
              ]
            },
            {
              "id": 2,
              "keyActions": []
            }
          ]
        },
        {
          "id": "mod",
          "modules": [
            {
              "id": 0,
              "keyActions": [
                {
                  "keyActionType": "keystroke",
                  "type": "basic",
                  "scancode": 64
                },
                {
                  "keyActionType": "keystroke",
                  "type": "basic",
                  "scancode": 65
                },
                {
                  "keyActionType": "keystroke",
                  "type": "basic",
                  "scancode": 66
                },
                {
                  "keyActionType": "keystroke",
                  "type": "basic",
                  "scancode": 67
                },
                {
                  "keyActionType": "keystroke",
                  "type": "basic",
                  "scancode": 68
                },
                {
                  "keyActionType": "keystroke",
                  "type": "basic",
                  "scancode": 69
                },
                {
                  "keyActionType": "keystroke",
                  "type": "basic",
                  "scancode": 76
                },
                {
                  "keyActionType": "keystroke",
                  "type": "basic",
                  "scancode": 75
                },
                {
                  "keyActionType": "keystroke",
                  "type": "basic",
                  "scancode": 82
                },
                {
                  "keyActionType": "keystroke",
                  "type": "basic",
                  "scancode": 78
                },
                {
                  "keyActionType": "keystroke",
                  "type": "basic",
                  "scancode": 5,
                  "modifierMask": 1
                },
                {
                  "keyActionType": "none"
                },
                {
                  "keyActionType": "none"
                },
                {
                  "keyActionType": "none"
                },
                {
                  "keyActionType": "keystroke",
                  "type": "basic",
                  "scancode": 12,
                  "modifierMask": 1
                },
                {
                  "keyActionType": "keystroke",
                  "type": "basic",
                  "scancode": 80
                },
                {
                  "keyActionType": "keystroke",
                  "type": "basic",
                  "scancode": 81
                },
                {
                  "keyActionType": "keystroke",
                  "type": "basic",
                  "scancode": 79
                },
                {
                  "keyActionType": "keystroke",
                  "type": "basic",
                  "scancode": 77
                },
                {
                  "keyActionType": "none"
                },
                {
                  "keyActionType": "keystroke",
                  "type": "basic",
                  "scancode": 40
                },
                {
                  "keyActionType": "keystroke",
                  "type": "basic",
                  "scancode": 74
                },
                {
                  "keyActionType": "mouse",
                  "mouseAction": "accelerate"
                },
                {
                  "keyActionType": "mouse",
                  "mouseAction": "leftClick"
                },
                {
                  "keyActionType": "mouse",
                  "mouseAction": "middleClick"
                },
                {
                  "keyActionType": "mouse",
                  "mouseAction": "rightClick"
                },
                {
                  "keyActionType": "mouse",
                  "mouseAction": "decelerate"
                },
                {
                  "keyActionType": "keystroke",
                  "type": "basic",
                  "modifierMask": 32
                },
                {
                  "keyActionType": "none"
                },
                {
                  "keyActionType": "mouse",
                  "mouseAction": "accelerate"
                },
                {
                  "keyActionType": "keystroke",
                  "type": "basic",
                  "scancode": 40
                },
                {
                  "keyActionType": "keystroke",
                  "type": "basic",
                  "modifierMask": 128
                },
                {
                  "keyActionType": "keystroke",
                  "type": "basic",
                  "modifierMask": 64
                },
                {
                  "keyActionType": "none"
                },
                {
                  "keyActionType": "keystroke",
                  "type": "basic",
                  "modifierMask": 16
                }
              ]
            },
            {
              "id": 1,
              "keyActions": [
                {
                  "keyActionType": "keystroke",
                  "type": "basic",
                  "scancode": 41
                },
                {
                  "keyActionType": "keystroke",
                  "type": "basic",
                  "scancode": 58
                },
                {
                  "keyActionType": "keystroke",
                  "type": "basic",
                  "scancode": 59
                },
                {
                  "keyActionType": "keystroke",
                  "type": "basic",
                  "scancode": 60
                },
                {
                  "keyActionType": "keystroke",
                  "type": "basic",
                  "scancode": 61
                },
                {
                  "keyActionType": "keystroke",
                  "type": "basic",
                  "scancode": 62
                },
                {
                  "keyActionType": "keystroke",
                  "type": "basic",
                  "scancode": 63
                },
                {
                  "keyActionType": "keystroke",
                  "type": "basic",
                  "scancode": 43
                },
                {
                  "keyActionType": "keystroke",
                  "type": "basic",
                  "scancode": 56,
                  "modifierMask": 16
                },
                {
                  "keyActionType": "mouse",
                  "mouseAction": "scrollDown"
                },
                {
                  "keyActionType": "mouse",
                  "mouseAction": "moveUp"
                },
                {
                  "keyActionType": "mouse",
                  "mouseAction": "scrollUp"
                },
                {
                  "keyActionType": "none"
                },
                {
                  "keyActionType": "keystroke",
                  "type": "basic",
                  "scancode": 55,
                  "modifierMask": 16
                },
                {
                  "keyActionType": "keystroke",
                  "type": "basic",
                  "scancode": 57
                },
                {
                  "keyActionType": "mouse",
                  "mouseAction": "scrollLeft"
                },
                {
                  "keyActionType": "mouse",
                  "mouseAction": "moveLeft"
                },
                {
                  "keyActionType": "mouse",
                  "mouseAction": "moveDown"
                },
                {
                  "keyActionType": "mouse",
                  "mouseAction": "moveRight"
                },
                {
                  "keyActionType": "none"
                },
                {
                  "keyActionType": "mouse",
                  "mouseAction": "scrollRight"
                },
                {
                  "keyActionType": "keystroke",
                  "type": "basic",
                  "modifierMask": 2
                },
                {
                  "keyActionType": "none"
                },
                {
                  "keyActionType": "keystroke",
                  "type": "media",
                  "scancode": 234
                },
                {
                  "keyActionType": "keystroke",
                  "type": "media",
                  "scancode": 233
                },
                {
                  "keyActionType": "keystroke",
                  "type": "media",
                  "scancode": 182
                },
                {
                  "keyActionType": "keystroke",
                  "type": "media",
                  "scancode": 205
                },
                {
                  "keyActionType": "keystroke",
                  "type": "media",
                  "scancode": 181
                },
                {
                  "keyActionType": "keystroke",
                  "type": "basic",
                  "modifierMask": 1
                },
                {
                  "keyActionType": "none"
                },
                {
                  "keyActionType": "keystroke",
                  "type": "basic",
                  "modifierMask": 4
                },
                {
                  "keyActionType": "keystroke",
                  "type": "basic",
                  "modifierMask": 8
                },
                {
                  "keyActionType": "keystroke",
                  "type": "basic",
                  "scancode": 44
                },
                {
                  "keyActionType": "switchLayer",
                  "layer": "mod",
                  "switchLayerMode": "hold"
                },
                {
                  "keyActionType": "none"
                }
              ]
            }
          ]
        },
        {
          "id": "fn",
          "modules": [
            {
              "id": 0,
              "keyActions": [
                {
                  "keyActionType": "none"
                },
                {
                  "keyActionType": "none"
                },
                {
                  "keyActionType": "none"
                },
                {
                  "keyActionType": "none"
                },
                {
                  "keyActionType": "none"
                },
                {
                  "keyActionType": "keystroke",
                  "type": "system",
                  "scancode": 129
                },
                {
                  "keyActionType": "none"
                },
                {
                  "keyActionType": "none"
                },
                {
                  "keyActionType": "none"
                },
                {
                  "keyActionType": "none"
                },
                {
                  "keyActionType": "none"
                },
                {
                  "keyActionType": "none"
                },
                {
                  "keyActionType": "none"
                },
                {
                  "keyActionType": "keystroke",
                  "type": "system",
                  "scancode": 130
                },
                {
                  "keyActionType": "none"
                },
                {
                  "keyActionType": "none"
                },
                {
                  "keyActionType": "none"
                },
                {
                  "keyActionType": "none"
                },
                {
                  "keyActionType": "none"
                },
                {
                  "keyActionType": "none"
                },
                {
                  "keyActionType": "keystroke",
                  "type": "basic",
                  "scancode": 40
                },
                {
                  "keyActionType": "none"
                },
                {
                  "keyActionType": "none"
                },
                {
                  "keyActionType": "none"
                },
                {
                  "keyActionType": "none"
                },
                {
                  "keyActionType": "none"
                },
                {
                  "keyActionType": "none"
                },
                {
                  "keyActionType": "keystroke",
                  "type": "basic",
                  "modifierMask": 32
                },
                {
                  "keyActionType": "none"
                },
                {
                  "keyActionType": "keystroke",
                  "type": "basic",
                  "scancode": 44,
                  "secondaryRoleAction": "rightSuper"
                },
                {
                  "keyActionType": "none"
                },
                {
                  "keyActionType": "keystroke",
                  "type": "basic",
                  "modifierMask": 128
                },
                {
                  "keyActionType": "keystroke",
                  "type": "basic",
                  "modifierMask": 64
                },
                {
                  "keyActionType": "switchLayer",
                  "layer": "fn",
                  "switchLayerMode": "hold"
                },
                {
                  "keyActionType": "keystroke",
                  "type": "basic",
                  "modifierMask": 16
                }
              ]
            },
            {
              "id": 1,
              "keyActions": [
                {
                  "keyActionType": "none"
                },
                {
                  "keyActionType": "none"
                },
                {
                  "keyActionType": "none"
                },
                {
                  "keyActionType": "none"
                },
                {
                  "keyActionType": "none"
                },
                {
                  "keyActionType": "none"
                },
                {
                  "keyActionType": "none"
                },
                {
                  "keyActionType": "keystroke",
                  "type": "basic",
                  "scancode": 43
                },
                {
                  "keyActionType": "none"
                },
                {
                  "keyActionType": "none"
                },
                {
                  "keyActionType": "none"
                },
                {
                  "keyActionType": "none"
                },
                {
                  "keyActionType": "none"
                },
                {
                  "keyActionType": "none"
                },
                {
                  "keyActionType": "keystroke",
                  "type": "basic",
                  "scancode": 57
                },
                {
                  "keyActionType": "none"
                },
                {
                  "keyActionType": "none"
                },
                {
                  "keyActionType": "none"
                },
                {
                  "keyActionType": "none"
                },
                {
                  "keyActionType": "none"
                },
                {
                  "keyActionType": "none"
                },
                {
                  "keyActionType": "keystroke",
                  "type": "basic",
                  "modifierMask": 2
                },
                {
                  "keyActionType": "none"
                },
                {
                  "keyActionType": "none"
                },
                {
                  "keyActionType": "none"
                },
                {
                  "keyActionType": "none"
                },
                {
                  "keyActionType": "none"
                },
                {
                  "keyActionType": "none"
                },
                {
                  "keyActionType": "keystroke",
                  "type": "basic",
                  "modifierMask": 1
                },
                {
                  "keyActionType": "switchLayer",
                  "layer": "fn",
                  "switchLayerMode": "hold"
                },
                {
                  "keyActionType": "keystroke",
                  "type": "basic",
                  "modifierMask": 4
                },
                {
                  "keyActionType": "keystroke",
                  "type": "basic",
                  "modifierMask": 8
                },
                {
                  "keyActionType": "keystroke",
                  "type": "basic",
                  "scancode": 44
                },
                {
                  "keyActionType": "switchKeymap",
                  "keymapAbbreviation": "UHK"
                },
                {
                  "keyActionType": "none"
                }
              ]
            }
          ]
        },
        {
          "id": "mouse",
          "modules": [
            {
              "id": 0,
              "keyActions": [
                {
                  "keyActionType": "none"
                },
                {
                  "keyActionType": "none"
                },
                {
                  "keyActionType": "none"
                },
                {
                  "keyActionType": "none"
                },
                {
                  "keyActionType": "none"
                },
                {
                  "keyActionType": "none"
                },
                {
                  "keyActionType": "none"
                },
                {
                  "keyActionType": "mouse",
                  "mouseAction": "scrollUp"
                },
                {
                  "keyActionType": "mouse",
                  "mouseAction": "moveUp"
                },
                {
                  "keyActionType": "mouse",
                  "mouseAction": "scrollDown"
                },
                {
                  "keyActionType": "none"
                },
                {
                  "keyActionType": "none"
                },
                {
                  "keyActionType": "none"
                },
                {
                  "keyActionType": "keystroke",
                  "type": "basic",
                  "modifierMask": 64
                },
                {
                  "keyActionType": "none"
                },
                {
                  "keyActionType": "mouse",
                  "mouseAction": "moveLeft"
                },
                {
                  "keyActionType": "mouse",
                  "mouseAction": "moveDown"
                },
                {
                  "keyActionType": "mouse",
                  "mouseAction": "moveRight"
                },
                {
                  "keyActionType": "mouse",
                  "mouseAction": "scrollRight"
                },
                {
                  "keyActionType": "none"
                },
                {
                  "keyActionType": "keystroke",
                  "type": "basic",
                  "scancode": 40
                },
                {
                  "keyActionType": "mouse",
                  "mouseAction": "scrollLeft"
                },
                {
                  "keyActionType": "none"
                },
                {
                  "keyActionType": "none"
                },
                {
                  "keyActionType": "none"
                },
                {
                  "keyActionType": "none"
                },
                {
                  "keyActionType": "none"
                },
                {
                  "keyActionType": "none"
                },
                {
                  "keyActionType": "none"
                },
                {
                  "keyActionType": "mouse",
                  "mouseAction": "leftClick"
                },
                {
                  "keyActionType": "none"
                },
                {
                  "keyActionType": "keystroke",
                  "type": "basic",
                  "modifierMask": 128
                },
                {
                  "keyActionType": "keystroke",
                  "type": "basic",
                  "modifierMask": 64
                },
                {
                  "keyActionType": "none"
                },
                {
                  "keyActionType": "keystroke",
                  "type": "basic",
                  "modifierMask": 16
                }
              ]
            },
            {
              "id": 1,
              "keyActions": [
                {
                  "keyActionType": "none"
                },
                {
                  "keyActionType": "none"
                },
                {
                  "keyActionType": "none"
                },
                {
                  "keyActionType": "none"
                },
                {
                  "keyActionType": "none"
                },
                {
                  "keyActionType": "none"
                },
                {
                  "keyActionType": "none"
                },
                {
                  "keyActionType": "keystroke",
                  "type": "basic",
                  "scancode": 43
                },
                {
                  "keyActionType": "none"
                },
                {
                  "keyActionType": "none"
                },
                {
                  "keyActionType": "none"
                },
                {
                  "keyActionType": "none"
                },
                {
                  "keyActionType": "none"
                },
                {
                  "keyActionType": "none"
                },
                {
                  "keyActionType": "keystroke",
                  "type": "basic",
                  "scancode": 57
                },
                {
                  "keyActionType": "none"
                },
                {
                  "keyActionType": "mouse",
                  "mouseAction": "rightClick"
                },
                {
                  "keyActionType": "mouse",
                  "mouseAction": "middleClick"
                },
                {
                  "keyActionType": "mouse",
                  "mouseAction": "leftClick"
                },
                {
                  "keyActionType": "none"
                },
                {
                  "keyActionType": "none"
                },
                {
                  "keyActionType": "none"
                },
                {
                  "keyActionType": "none"
                },
                {
                  "keyActionType": "none"
                },
                {
                  "keyActionType": "none"
                },
                {
                  "keyActionType": "none"
                },
                {
                  "keyActionType": "none"
                },
                {
                  "keyActionType": "none"
                },
                {
                  "keyActionType": "keystroke",
                  "type": "basic",
                  "modifierMask": 1
                },
                {
                  "keyActionType": "none"
                },
                {
                  "keyActionType": "keystroke",
                  "type": "basic",
                  "modifierMask": 4
                },
                {
                  "keyActionType": "keystroke",
                  "type": "basic",
                  "modifierMask": 8
                },
                {
                  "keyActionType": "keystroke",
                  "type": "basic",
                  "scancode": 44
                },
                {
                  "keyActionType": "mouse",
                  "mouseAction": "accelerate"
                },
                {
                  "keyActionType": "none"
                }
              ]
            }
          ]
        }
      ]
    },
    {
      "isDefault": true,
      "abbreviation": "UHK",
      "name": "Main",
      "description": "main layout",
      "layers": [
        {
          "id": "base",
          "modules": [
            {
              "id": 0,
              "keyActions": [
                {
                  "keyActionType": "keystroke",
                  "type": "basic",
                  "scancode": 36
                },
                {
                  "keyActionType": "keystroke",
                  "type": "basic",
                  "scancode": 37
                },
                {
                  "keyActionType": "keystroke",
                  "type": "basic",
                  "scancode": 38
                },
                {
                  "keyActionType": "keystroke",
                  "type": "basic",
                  "scancode": 39
                },
                {
                  "keyActionType": "keystroke",
                  "type": "basic",
                  "scancode": 45
                },
                {
                  "keyActionType": "keystroke",
                  "type": "basic",
                  "scancode": 46
                },
                {
                  "keyActionType": "keystroke",
                  "type": "basic",
                  "scancode": 42
                },
                {
                  "keyActionType": "keystroke",
                  "type": "basic",
                  "scancode": 24
                },
                {
                  "keyActionType": "keystroke",
                  "type": "basic",
                  "scancode": 12
                },
                {
                  "keyActionType": "keystroke",
                  "type": "basic",
                  "scancode": 18
                },
                {
                  "keyActionType": "keystroke",
                  "type": "basic",
                  "scancode": 19
                },
                {
                  "keyActionType": "keystroke",
                  "type": "basic",
                  "scancode": 47
                },
                {
                  "keyActionType": "keystroke",
                  "type": "basic",
                  "scancode": 48
                },
                {
                  "keyActionType": "keystroke",
                  "type": "basic",
                  "scancode": 49
                },
                {
                  "keyActionType": "keystroke",
                  "type": "basic",
                  "scancode": 28
                },
                {
                  "keyActionType": "keystroke",
                  "type": "basic",
                  "scancode": 13
                },
                {
                  "keyActionType": "keystroke",
                  "type": "basic",
                  "scancode": 14
                },
                {
                  "keyActionType": "keystroke",
                  "type": "basic",
                  "scancode": 15
                },
                {
                  "keyActionType": "keystroke",
                  "type": "basic",
                  "scancode": 51
                },
                {
                  "keyActionType": "keystroke",
                  "type": "basic",
                  "scancode": 52
                },
                {
                  "keyActionType": "keystroke",
                  "type": "basic",
                  "modifierMask": 16
                },
                {
                  "keyActionType": "keystroke",
                  "type": "basic",
                  "scancode": 11
                },
                {
                  "keyActionType": "keystroke",
                  "type": "basic",
                  "scancode": 17
                },
                {
                  "keyActionType": "keystroke",
                  "type": "basic",
                  "scancode": 16
                },
                {
                  "keyActionType": "keystroke",
                  "type": "basic",
                  "scancode": 54
                },
                {
                  "keyActionType": "keystroke",
                  "type": "basic",
                  "scancode": 55
                },
                {
                  "keyActionType": "keystroke",
                  "type": "basic",
                  "scancode": 56
                },
                {
                  "keyActionType": "keystroke",
                  "type": "basic",
                  "modifierMask": 32
                },
                {
                  "keyActionType": "none"
                },
                {
                  "keyActionType": "keystroke",
                  "type": "basic",
                  "scancode": 44
                },
                {
                  "keyActionType": "keystroke",
                  "type": "basic",
                  "scancode": 40
                },
                {
                  "keyActionType": "keystroke",
                  "type": "basic",
                  "modifierMask": 128
                },
                {
                  "keyActionType": "keystroke",
                  "type": "basic",
                  "scancode": 101,
                  "modifierMask": 16
                },
                {
                  "keyActionType": "switchLayer",
                  "layer": "fn",
                  "switchLayerMode": "hold"
                },
                {
                  "keyActionType": "keystroke",
                  "type": "basic",
                  "modifierMask": 64
                }
              ]
            },
            {
              "id": 1,
              "keyActions": [
                {
                  "keyActionType": "keystroke",
                  "type": "basic",
                  "scancode": 53
                },
                {
                  "keyActionType": "keystroke",
                  "type": "basic",
                  "scancode": 30
                },
                {
                  "keyActionType": "keystroke",
                  "type": "basic",
                  "scancode": 31
                },
                {
                  "keyActionType": "keystroke",
                  "type": "basic",
                  "scancode": 32
                },
                {
                  "keyActionType": "keystroke",
                  "type": "basic",
                  "scancode": 33
                },
                {
                  "keyActionType": "keystroke",
                  "type": "basic",
                  "scancode": 34
                },
                {
                  "keyActionType": "keystroke",
                  "type": "basic",
                  "scancode": 35
                },
                {
                  "keyActionType": "keystroke",
                  "type": "basic",
                  "scancode": 43
                },
                {
                  "keyActionType": "keystroke",
                  "type": "basic",
                  "scancode": 20
                },
                {
                  "keyActionType": "keystroke",
                  "type": "basic",
                  "scancode": 26
                },
                {
                  "keyActionType": "keystroke",
                  "type": "basic",
                  "scancode": 8
                },
                {
                  "keyActionType": "keystroke",
                  "type": "basic",
                  "scancode": 21
                },
                {
                  "keyActionType": "none"
                },
                {
                  "keyActionType": "keystroke",
                  "type": "basic",
                  "scancode": 23
                },
                {
                  "keyActionType": "keystroke",
                  "type": "basic",
                  "modifierMask": 1
                },
                {
                  "keyActionType": "keystroke",
                  "type": "basic",
                  "scancode": 4
                },
                {
                  "keyActionType": "keystroke",
                  "type": "basic",
                  "scancode": 22
                },
                {
                  "keyActionType": "keystroke",
                  "type": "basic",
                  "scancode": 7
                },
                {
                  "keyActionType": "keystroke",
                  "type": "basic",
                  "scancode": 9
                },
                {
                  "keyActionType": "none"
                },
                {
                  "keyActionType": "keystroke",
                  "type": "basic",
                  "scancode": 10
                },
                {
                  "keyActionType": "keystroke",
                  "type": "basic",
                  "modifierMask": 2
                },
                {
                  "keyActionType": "keystroke",
                  "type": "basic",
                  "scancode": 100
                },
                {
                  "keyActionType": "keystroke",
                  "type": "basic",
                  "scancode": 29
                },
                {
                  "keyActionType": "keystroke",
                  "type": "basic",
                  "scancode": 27
                },
                {
                  "keyActionType": "keystroke",
                  "type": "basic",
                  "scancode": 6
                },
                {
                  "keyActionType": "keystroke",
                  "type": "basic",
                  "scancode": 25
                },
                {
                  "keyActionType": "keystroke",
                  "type": "basic",
                  "scancode": 5
                },
                {
                  "keyActionType": "keystroke",
                  "type": "basic",
                  "modifierMask": 4
                },
                {
                  "keyActionType": "switchLayer",
                  "layer": "fn",
                  "switchLayerMode": "hold"
                },
                {
                  "keyActionType": "keystroke",
                  "type": "basic",
                  "modifierMask": 9
                },
                {
                  "keyActionType": "keystroke",
                  "type": "basic",
                  "modifierMask": 8
                },
                {
                  "keyActionType": "keystroke",
                  "type": "basic",
                  "scancode": 41
                },
                {
                  "keyActionType": "switchLayer",
                  "layer": "mod",
                  "switchLayerMode": "hold"
                },
                {
                  "keyActionType": "none"
                }
              ]
            },
            {
              "id": 2,
              "keyActions": []
            }
          ]
        },
        {
          "id": "mod",
          "modules": [
            {
              "id": 0,
              "keyActions": [
                {
                  "keyActionType": "keystroke",
                  "type": "basic",
                  "scancode": 64
                },
                {
                  "keyActionType": "keystroke",
                  "type": "basic",
                  "scancode": 65
                },
                {
                  "keyActionType": "keystroke",
                  "type": "basic",
                  "scancode": 66
                },
                {
                  "keyActionType": "keystroke",
                  "type": "basic",
                  "scancode": 67
                },
                {
                  "keyActionType": "keystroke",
                  "type": "basic",
                  "scancode": 68
                },
                {
                  "keyActionType": "keystroke",
                  "type": "basic",
                  "scancode": 69
                },
                {
                  "keyActionType": "keystroke",
                  "type": "basic",
                  "scancode": 76
                },
                {
                  "keyActionType": "keystroke",
                  "type": "basic",
                  "scancode": 75
                },
                {
                  "keyActionType": "keystroke",
                  "type": "basic",
                  "scancode": 82
                },
                {
                  "keyActionType": "keystroke",
                  "type": "basic",
                  "scancode": 78
                },
                {
                  "keyActionType": "keystroke",
                  "type": "basic",
                  "scancode": 5,
                  "modifierMask": 1
                },
                {
                  "keyActionType": "none"
                },
                {
                  "keyActionType": "none"
                },
                {
                  "keyActionType": "none"
                },
                {
                  "keyActionType": "keystroke",
                  "type": "basic",
                  "scancode": 12,
                  "modifierMask": 1
                },
                {
                  "keyActionType": "keystroke",
                  "type": "basic",
                  "scancode": 80
                },
                {
                  "keyActionType": "keystroke",
                  "type": "basic",
                  "scancode": 81
                },
                {
                  "keyActionType": "keystroke",
                  "type": "basic",
                  "scancode": 79
                },
                {
                  "keyActionType": "keystroke",
                  "type": "basic",
                  "scancode": 77
                },
                {
                  "keyActionType": "none"
                },
                {
                  "keyActionType": "keystroke",
                  "type": "basic",
                  "modifierMask": 16
                },
                {
                  "keyActionType": "keystroke",
                  "type": "basic",
                  "scancode": 74
                },
                {
                  "keyActionType": "mouse",
                  "mouseAction": "accelerate"
                },
                {
                  "keyActionType": "mouse",
                  "mouseAction": "leftClick"
                },
                {
                  "keyActionType": "mouse",
                  "mouseAction": "middleClick"
                },
                {
                  "keyActionType": "mouse",
                  "mouseAction": "rightClick"
                },
                {
                  "keyActionType": "mouse",
                  "mouseAction": "decelerate"
                },
                {
                  "keyActionType": "keystroke",
                  "type": "basic",
                  "modifierMask": 32
                },
                {
                  "keyActionType": "none"
                },
                {
                  "keyActionType": "keystroke",
                  "type": "basic",
                  "scancode": 69
                },
                {
                  "keyActionType": "keystroke",
                  "type": "basic",
                  "scancode": 40
                },
                {
                  "keyActionType": "keystroke",
                  "type": "basic",
                  "modifierMask": 128
                },
                {
                  "keyActionType": "keystroke",
                  "type": "basic",
                  "scancode": 145
                },
                {
                  "keyActionType": "none"
                },
                {
                  "keyActionType": "keystroke",
                  "type": "basic",
                  "modifierMask": 64
                }
              ]
            },
            {
              "id": 1,
              "keyActions": [
                {
                  "keyActionType": "keystroke",
                  "type": "basic",
                  "scancode": 57
                },
                {
                  "keyActionType": "keystroke",
                  "type": "basic",
                  "scancode": 58
                },
                {
                  "keyActionType": "keystroke",
                  "type": "basic",
                  "scancode": 59
                },
                {
                  "keyActionType": "keystroke",
                  "type": "basic",
                  "scancode": 60
                },
                {
                  "keyActionType": "keystroke",
                  "type": "basic",
                  "scancode": 61
                },
                {
                  "keyActionType": "keystroke",
                  "type": "basic",
                  "scancode": 62
                },
                {
                  "keyActionType": "keystroke",
                  "type": "basic",
                  "scancode": 63
                },
                {
                  "keyActionType": "keystroke",
                  "type": "basic",
                  "scancode": 43
                },
                {
                  "keyActionType": "keystroke",
                  "type": "basic",
                  "scancode": 56,
                  "modifierMask": 16
                },
                {
                  "keyActionType": "mouse",
                  "mouseAction": "scrollDown"
                },
                {
                  "keyActionType": "mouse",
                  "mouseAction": "moveUp"
                },
                {
                  "keyActionType": "mouse",
                  "mouseAction": "scrollUp"
                },
                {
                  "keyActionType": "none"
                },
                {
                  "keyActionType": "keystroke",
                  "type": "basic",
                  "scancode": 55,
                  "modifierMask": 16
                },
                {
                  "keyActionType": "keystroke",
                  "type": "basic",
                  "modifierMask": 1
                },
                {
                  "keyActionType": "mouse",
                  "mouseAction": "scrollLeft"
                },
                {
                  "keyActionType": "mouse",
                  "mouseAction": "moveLeft"
                },
                {
                  "keyActionType": "mouse",
                  "mouseAction": "moveDown"
                },
                {
                  "keyActionType": "mouse",
                  "mouseAction": "moveRight"
                },
                {
                  "keyActionType": "none"
                },
                {
                  "keyActionType": "mouse",
                  "mouseAction": "scrollRight"
                },
                {
                  "keyActionType": "keystroke",
                  "type": "basic",
                  "modifierMask": 2
                },
                {
                  "keyActionType": "none"
                },
                {
                  "keyActionType": "keystroke",
                  "type": "media",
                  "scancode": 234
                },
                {
                  "keyActionType": "keystroke",
                  "type": "media",
                  "scancode": 233
                },
                {
                  "keyActionType": "keystroke",
                  "type": "media",
                  "scancode": 182
                },
                {
                  "keyActionType": "keystroke",
                  "type": "media",
                  "scancode": 205
                },
                {
                  "keyActionType": "keystroke",
                  "type": "media",
                  "scancode": 181
                },
                {
                  "keyActionType": "keystroke",
                  "type": "basic",
                  "modifierMask": 4
                },
                {
                  "keyActionType": "none"
                },
                {
                  "keyActionType": "keystroke",
                  "type": "basic",
                  "scancode": 144
                },
                {
                  "keyActionType": "keystroke",
                  "type": "basic",
                  "modifierMask": 8
                },
                {
                  "keyActionType": "keystroke",
                  "type": "basic",
                  "scancode": 41
                },
                {
                  "keyActionType": "switchLayer",
                  "layer": "mod",
                  "switchLayerMode": "hold"
                },
                {
                  "keyActionType": "none"
                }
              ]
            }
          ]
        },
        {
          "id": "fn",
          "modules": [
            {
              "id": 0,
              "keyActions": [
                {
                  "keyActionType": "none"
                },
                {
                  "keyActionType": "none"
                },
                {
                  "keyActionType": "none"
                },
                {
                  "keyActionType": "none"
                },
                {
                  "keyActionType": "none"
                },
                {
                  "keyActionType": "keystroke",
                  "type": "system",
                  "scancode": 129
                },
                {
                  "keyActionType": "none"
                },
                {
                  "keyActionType": "none"
                },
                {
                  "keyActionType": "none"
                },
                {
                  "keyActionType": "none"
                },
                {
                  "keyActionType": "none"
                },
                {
                  "keyActionType": "none"
                },
                {
                  "keyActionType": "none"
                },
                {
                  "keyActionType": "keystroke",
                  "type": "system",
                  "scancode": 130
                },
                {
                  "keyActionType": "none"
                },
                {
                  "keyActionType": "none"
                },
                {
                  "keyActionType": "none"
                },
                {
                  "keyActionType": "none"
                },
                {
                  "keyActionType": "none"
                },
                {
                  "keyActionType": "none"
                },
                {
                  "keyActionType": "keystroke",
                  "type": "basic",
                  "modifierMask": 16
                },
                {
                  "keyActionType": "none"
                },
                {
                  "keyActionType": "none"
                },
                {
                  "keyActionType": "none"
                },
                {
                  "keyActionType": "none"
                },
                {
                  "keyActionType": "none"
                },
                {
                  "keyActionType": "none"
                },
                {
                  "keyActionType": "keystroke",
                  "type": "basic",
                  "modifierMask": 32
                },
                {
                  "keyActionType": "none"
                },
                {
                  "keyActionType": "keystroke",
                  "type": "basic",
                  "scancode": 44,
                  "secondaryRoleAction": "rightSuper"
                },
                {
                  "keyActionType": "none"
                },
                {
                  "keyActionType": "keystroke",
                  "type": "basic",
                  "modifierMask": 128
                },
                {
                  "keyActionType": "keystroke",
                  "type": "basic",
                  "scancode": 145
                },
                {
                  "keyActionType": "switchLayer",
                  "layer": "fn",
                  "switchLayerMode": "hold"
                },
                {
                  "keyActionType": "keystroke",
                  "type": "basic",
                  "modifierMask": 64
                }
              ]
            },
            {
              "id": 1,
              "keyActions": [
                {
                  "keyActionType": "none"
                },
                {
                  "keyActionType": "none"
                },
                {
                  "keyActionType": "none"
                },
                {
                  "keyActionType": "none"
                },
                {
                  "keyActionType": "none"
                },
                {
                  "keyActionType": "none"
                },
                {
                  "keyActionType": "none"
                },
                {
                  "keyActionType": "keystroke",
                  "type": "basic",
                  "scancode": 43
                },
                {
                  "keyActionType": "none"
                },
                {
                  "keyActionType": "none"
                },
                {
                  "keyActionType": "none"
                },
                {
                  "keyActionType": "none"
                },
                {
                  "keyActionType": "none"
                },
                {
                  "keyActionType": "none"
                },
                {
                  "keyActionType": "keystroke",
                  "type": "basic",
                  "modifierMask": 1
                },
                {
                  "keyActionType": "none"
                },
                {
                  "keyActionType": "none"
                },
                {
                  "keyActionType": "none"
                },
                {
                  "keyActionType": "none"
                },
                {
                  "keyActionType": "none"
                },
                {
                  "keyActionType": "none"
                },
                {
                  "keyActionType": "keystroke",
                  "type": "basic",
                  "modifierMask": 2
                },
                {
                  "keyActionType": "none"
                },
                {
                  "keyActionType": "none"
                },
                {
                  "keyActionType": "none"
                },
                {
                  "keyActionType": "none"
                },
                {
                  "keyActionType": "none"
                },
                {
                  "keyActionType": "none"
                },
                {
                  "keyActionType": "keystroke",
                  "type": "basic",
                  "modifierMask": 4
                },
                {
                  "keyActionType": "switchLayer",
                  "layer": "fn",
                  "switchLayerMode": "hold"
                },
                {
                  "keyActionType": "keystroke",
                  "type": "basic",
                  "scancode": 144
                },
                {
                  "keyActionType": "keystroke",
                  "type": "basic",
                  "modifierMask": 8
                },
                {
                  "keyActionType": "none"
                },
                {
                  "keyActionType": "switchKeymap",
                  "keymapAbbreviation": "GAM"
                },
                {
                  "keyActionType": "none"
                }
              ]
            }
          ]
        },
        {
          "id": "mouse",
          "modules": [
            {
              "id": 0,
              "keyActions": [
                {
                  "keyActionType": "none"
                },
                {
                  "keyActionType": "none"
                },
                {
                  "keyActionType": "none"
                },
                {
                  "keyActionType": "none"
                },
                {
                  "keyActionType": "none"
                },
                {
                  "keyActionType": "none"
                },
                {
                  "keyActionType": "none"
                },
                {
                  "keyActionType": "mouse",
                  "mouseAction": "scrollUp"
                },
                {
                  "keyActionType": "mouse",
                  "mouseAction": "moveUp"
                },
                {
                  "keyActionType": "mouse",
                  "mouseAction": "scrollDown"
                },
                {
                  "keyActionType": "none"
                },
                {
                  "keyActionType": "none"
                },
                {
                  "keyActionType": "none"
                },
                {
                  "keyActionType": "keystroke",
                  "type": "basic",
                  "modifierMask": 64
                },
                {
                  "keyActionType": "none"
                },
                {
                  "keyActionType": "mouse",
                  "mouseAction": "moveLeft"
                },
                {
                  "keyActionType": "mouse",
                  "mouseAction": "moveDown"
                },
                {
                  "keyActionType": "mouse",
                  "mouseAction": "moveRight"
                },
                {
                  "keyActionType": "mouse",
                  "mouseAction": "scrollRight"
                },
                {
                  "keyActionType": "none"
                },
                {
                  "keyActionType": "keystroke",
                  "type": "basic",
                  "modifierMask": 16
                },
                {
                  "keyActionType": "mouse",
                  "mouseAction": "scrollLeft"
                },
                {
                  "keyActionType": "none"
                },
                {
                  "keyActionType": "none"
                },
                {
                  "keyActionType": "none"
                },
                {
                  "keyActionType": "none"
                },
                {
                  "keyActionType": "none"
                },
                {
                  "keyActionType": "none"
                },
                {
                  "keyActionType": "none"
                },
                {
                  "keyActionType": "mouse",
                  "mouseAction": "leftClick"
                },
                {
                  "keyActionType": "none"
                },
                {
                  "keyActionType": "keystroke",
                  "type": "basic",
                  "modifierMask": 128
                },
                {
                  "keyActionType": "keystroke",
                  "type": "basic",
                  "modifierMask": 64
                },
                {
                  "keyActionType": "none"
                },
                {
                  "keyActionType": "keystroke",
                  "type": "basic",
                  "modifierMask": 64
                }
              ]
            },
            {
              "id": 1,
              "keyActions": [
                {
                  "keyActionType": "none"
                },
                {
                  "keyActionType": "none"
                },
                {
                  "keyActionType": "none"
                },
                {
                  "keyActionType": "none"
                },
                {
                  "keyActionType": "none"
                },
                {
                  "keyActionType": "none"
                },
                {
                  "keyActionType": "none"
                },
                {
                  "keyActionType": "keystroke",
                  "type": "basic",
                  "scancode": 43
                },
                {
                  "keyActionType": "none"
                },
                {
                  "keyActionType": "none"
                },
                {
                  "keyActionType": "none"
                },
                {
                  "keyActionType": "none"
                },
                {
                  "keyActionType": "none"
                },
                {
                  "keyActionType": "none"
                },
                {
                  "keyActionType": "none"
                },
                {
                  "keyActionType": "none"
                },
                {
                  "keyActionType": "mouse",
                  "mouseAction": "rightClick"
                },
                {
                  "keyActionType": "mouse",
                  "mouseAction": "middleClick"
                },
                {
                  "keyActionType": "mouse",
                  "mouseAction": "leftClick"
                },
                {
                  "keyActionType": "none"
                },
                {
                  "keyActionType": "none"
                },
                {
                  "keyActionType": "none"
                },
                {
                  "keyActionType": "none"
                },
                {
                  "keyActionType": "none"
                },
                {
                  "keyActionType": "none"
                },
                {
                  "keyActionType": "none"
                },
                {
                  "keyActionType": "none"
                },
                {
                  "keyActionType": "none"
                },
                {
                  "keyActionType": "keystroke",
                  "type": "basic",
                  "modifierMask": 4
                },
                {
                  "keyActionType": "none"
                },
                {
                  "keyActionType": "keystroke",
                  "type": "basic",
                  "modifierMask": 4
                },
                {
                  "keyActionType": "keystroke",
                  "type": "basic",
                  "modifierMask": 8
                },
                {
                  "keyActionType": "none"
                },
                {
                  "keyActionType": "mouse",
                  "mouseAction": "accelerate"
                },
                {
                  "keyActionType": "none"
                }
              ]
            }
          ]
        }
      ]
    }
  ],
  "macros": [
    {
      "isLooped": false,
      "isPrivate": true,
      "name": "Petr",
      "macroActions": [
        {
          "macroActionType": "text",
          "text": "petr.kozorezov"
        }
      ]
    }
  ]
}